setup.py
ps_probability/Binomialdistribution.py
ps_probability/Gaussiandistribution.py
ps_probability/Generaldistribution.py
ps_probability/__init__.py
ps_probability.egg-info/PKG-INFO
ps_probability.egg-info/SOURCES.txt
ps_probability.egg-info/dependency_links.txt
ps_probability.egg-info/not-zip-safe
ps_probability.egg-info/top_level.txt