Metadata-Version: 1.0
Name: ps-probability
Version: 0.1
Summary: Binomial and Gaussian distributions
Home-page: UNKNOWN
Author: PINAKI SEN
Author-email: pinakisen.eenita@gmail.com
License: UNKNOWN
Platform: UNKNOWN
